bump_release/__init__.py
bump_release/__main__.py
bump_release/helpers.py
bump_release-0.10.6.dist-info/LICENSE
bump_release-0.10.6.dist-info/METADATA
bump_release-0.10.6.dist-info/WHEEL
bump_release-0.10.6.dist-info/entry_points.txt
bump_release-0.10.6.dist-info/top_level.txt
bump_release-0.10.6.dist-info/RECORD
