Metadata-Version: 2.1
Name: bump-release
Version: 0.10.6
Summary: Updates various version numbers for python projects
Author-email: François GUÉRIN <fguerin@ville-tourcoing.fr>
Project-URL: Homepage, https://github.com/frague59/bump-release
Classifier: Programming Language :: Python :: 3
Classifier: License :: OSI Approved :: MIT License
Classifier: Operating System :: OS Independent
Classifier: Development Status :: 4 - Beta
Classifier: Environment :: Console
Classifier: Intended Audience :: Developers
Classifier: Programming Language :: Python :: 3.7
Classifier: Programming Language :: Python :: 3.8
Classifier: Programming Language :: Python :: 3.9
Classifier: Programming Language :: Python :: 3.10
Classifier: Operating System :: POSIX
Classifier: Operating System :: POSIX :: Linux
Classifier: Topic :: Software Development
Classifier: Topic :: Software Development :: Version Control
Requires-Python: >=3.7
License-File: LICENSE
Requires-Dist: Click
Requires-Dist: ruamel.yaml
Provides-Extra: toml
Requires-Dist: tomli ; extra == 'toml'
Requires-Dist: tomli-w ; extra == 'toml'
